searchlib/__init__.py
searchlib/algorithms.py
searchlib/display.py
searchlib/eda.py
searchlib/plots.py
searchlib_khizer-0.1.dist-info/METADATA
searchlib_khizer-0.1.dist-info/WHEEL
searchlib_khizer-0.1.dist-info/top_level.txt
searchlib_khizer-0.1.dist-info/RECORD
