Metadata-Version: 2.1
Name: searchlib-khizer
Version: 0.1
Summary: A library to retrieve AI algorithm code snippets
Author: Your Name
